simplecmr/__init__.py
simplecmr/cli.py
simplecmr/query.py
simplecmr/result.py
simplecmr/utils.py
simplecmr-0.0.1.dist-info/METADATA
simplecmr-0.0.1.dist-info/RECORD
simplecmr-0.0.1.dist-info/WHEEL
simplecmr-0.0.1.dist-info/top_level.txt
