Metadata-Version: 2.1
Name: simplecmr
Version: 0.0.1
Summary: Simple CMR
Home-page: http://github.com/kmarkert/simple-cmr
Author: Kel Markert
Author-email: kel.markert@gmail.com
License: MIT
Platform: UNKNOWN
Requires-Dist: requests
Requires-Dist: requests-cache
